cs/sqltags.py
cs.sqltags-20240723.dist-info/METADATA
cs.sqltags-20240723.dist-info/WHEEL
cs.sqltags-20240723.dist-info/entry_points.txt
cs.sqltags-20240723.dist-info/top_level.txt
cs.sqltags-20240723.dist-info/RECORD
