Metadata-Version: 2.1
Name: cs.sqltags
Version: 20240723
Summary: Simple SQL based tagging and the associated `sqltags` command line script, supporting both tagged named objects and tagged timestamped log entries.
Author-email: Cameron Simpson <cs@cskk.id.au>
License: GNU General Public License v3 or later (GPLv3+)
Project-URL: Monorepo Hg/Mercurial Mirror, https://hg.sr.ht/~cameron-simpson/css
Project-URL: Monorepo Git Mirror, https://github.com/cameron-simpson/css
Project-URL: MonoRepo Commits, https://bitbucket.org/cameron_simpson/css/commits/branch/main
Project-URL: Source, https://github.com/cameron-simpson/css/blob/main/lib/python/cs/sqltags.py
Keywords: python3
Classifier: Programming Language :: Python
Classifier: Programming Language :: Python :: 3
Classifier: Development Status :: 4 - Beta
Classifier: Intended Audience :: Developers
Classifier: Operating System :: OS Independent
Classifier: Topic :: Software Development :: Libraries :: Python Modules
Classifier: License :: OSI Approved :: GNU General Public License v3 or later (GPLv3+)
Requires-Dist: cs.cmdutils >=20210404
Requires-Dist: cs.context >=20240630
Requires-Dist: cs.dateutils >=20230210
Requires-Dist: cs.deco >=20240709
Requires-Dist: cs.fileutils >=20240723
Requires-Dist: cs.lex >=20240630
Requires-Dist: cs.logutils >=20240630
Requires-Dist: cs.obj >=20220918
Requires-Dist: cs.pfx >=20240630
Requires-Dist: cs.sqlalchemy-utils >=20210420
Requires-Dist: cs.tagset >=20211212
Requires-Dist: cs.threads >=20201025
Requires-Dist: cs.upd >=20240630
Requires-Dist: icontract
Requires-Dist: sqlalchemy
Requires-Dist: typeguard
